{"window": ["2026-07-13", "2026-07-15"], "anchor": "2026-07-16", "kpi_day": 7416686, "per_ad_action": false, "accounts": {"VSTEP - 01": {"codes": [{"code": "704262", "name": "Ưu đãi - Cơ hội học VSTEP Hook 2", "rec": "SCALE +20%", "dir": "up", "budget": 1550000, "ads": 7}, {"code": "70226", "name": "Chào hè", "rec": "GIẢM 20% · 3d tụt, 7d còn tốt (theo dõi sát, chưa tắt)", "dir": "down", "budget": 0, "ads": 2}, {"code": "71026", "name": "Ưu đãi - Chào hè 45%", "rec": "SCALE +20%", "dir": "up", "budget": 707000, "ads": 3}, {"code": "708262", "name": "Lộ trình - 2k8 đạt điểm mục tiêu 2", "rec": "TẮT", "dir": "off", "budget": 0, "ads": 2}, {"code": "190626", "name": "Lộ trình - Quỳnh 1806", "rec": "SCALE +20%", "dir": "up", "budget": 230000, "ads": 3}, {"code": "62426", "name": "2008", "rec": "TẮT", "dir": "off", "budget": 0, "ads": 0}, {"code": "626265", "name": "Lộ trình - Khóa VSTEP có gì - Hook 5", "rec": "GIỮ · 3d tốt, 7d chưa xác nhận — scale nhẹ", "dir": "hold", "budget": 0, "ads": 3}, {"code": "712261", "name": "Cơn sóng layoff 1", "rec": "TẮT · Phiên 1 (cổng) — rất tệ", "dir": "off", "budget": 520000, "ads": 2}, {"code": "71126", "name": "Lộ trình - Lộ trình ngắn nhất", "rec": "GIỮ · Phiên 1 — vào Phiên 2", "dir": "hold", "budget": 0, "ads": 2}, {"code": "260611", "name": "Painpoints - Lý do thi trượt VSTEP", "rec": "GIỮ · 3d tốt, 7d chưa xác nhận — scale nhẹ", "dir": "hold", "budget": 418000, "ads": 2}, {"code": "712263", "name": "Cơn sóng layoff 3", "rec": "XEM XÉT TẮT · 0 lead, chi cao", "dir": "off", "budget": 0, "ads": 0}, {"code": "712262", "name": "Cơn sóng layoff 2", "rec": "XEM XÉT TẮT · 0 lead, chi cao", "dir": "off", "budget": 0, "ads": 0}], "kill_ads": [{"id": "120249598438130223", "code": "704262", "name": "Prep.070426-2_VSTEP25_Ưu đãi - Cơ hội học VS", "rec": "TẮT · Phiên 2 — rất tệ", "src": "ad lẻ"}, {"id": "120249625171140223", "code": "712261", "name": "Cơn sóng layoff 1", "rec": "TẮT · Phiên 1 (cổng) — rất tệ", "src": "content TẮT"}, {"id": "120249704814090223", "code": "712261", "name": "Cơn sóng layoff 1", "rec": "TẮT · Phiên 1 (cổng) — rất tệ", "src": "content TẮT"}, {"id": "120249596522080223", "code": "708262", "name": "Lộ trình - 2k8 đạt điểm mục ti", "rec": "TẮT", "src": "content TẮT"}, {"id": "120249596522070223", "code": "708262", "name": "Lộ trình - 2k8 đạt điểm mục ti", "rec": "TẮT", "src": "content TẮT"}], "scale_track": []}}}